shiptv/__init__.py
shiptv/cli.py
shiptv/shiptv.py
shiptv/variants.py
shiptv/tmpl/phylocanvas.html
shiptv/tmpl/phylocanvas_metadata_plugin.html
shiptv-0.4.1.dist-info/AUTHORS.rst
shiptv-0.4.1.dist-info/LICENSE
shiptv-0.4.1.dist-info/METADATA
shiptv-0.4.1.dist-info/WHEEL
shiptv-0.4.1.dist-info/entry_points.txt
shiptv-0.4.1.dist-info/top_level.txt
shiptv-0.4.1.dist-info/RECORD
