Metadata-Version: 2.1
Name: shiptv
Version: 0.4.1
Summary: Generate a standalone HTML file with an interactive phylogenetic tree using PhyloCanvas
Home-page: https://github.com/peterk87/shiptv
Author: Peter Kruczkiewicz
Author-email: peter.kruczkiewicz@gmail.com
License: Apache Software License 2.0
Keywords: shiptv
Platform: UNKNOWN
Classifier: Development Status :: 2 - Pre-Alpha
Classifier: Intended Audience :: Developers
Classifier: License :: OSI Approved :: Apache Software License
Classifier: Natural Language :: English
Classifier: Programming Language :: Python :: 3.6
Classifier: Programming Language :: Python :: 3.7
Classifier: Programming Language :: Python :: 3.8
Classifier: Programming Language :: Python :: 3.9
Requires-Dist: rich
Requires-Dist: typer
Requires-Dist: jinja2
Requires-Dist: pandas
Requires-Dist: biopython
Requires-Dist: requests
